sis_meta/__about__.py
sis_meta/__init__.py
sis_meta/regex.py
sis_meta/groups/__init__.py
sis_meta/groups/_parse.py
sis_meta/groups/_serialize.py
sis_meta/groups/groups.py
sis_meta/groups/templates/group.meta
sis_meta/groups/templates/group_header.meta
sis_meta/groups/templates/grouptree.meta
sis_meta/io/__init__.py
sis_meta/io/exceptions.py
sis_meta/io/read_meta.py
sis_meta/io/write_meta.py
sis_meta/io/templates/base.meta
sis_meta/mark/__init__.py
sis_meta/mark/_parse.py
sis_meta/mark/_serialize.py
sis_meta/mark/mark.py
sis_meta/mark/templates/marks_segment.meta
sis_meta/meta/__init__.py
sis_meta/meta/meta.py
sis_meta-1.0.0.dist-info/METADATA
sis_meta-1.0.0.dist-info/WHEEL
sis_meta-1.0.0.dist-info/licenses/LICENSE.txt
sis_meta-1.0.0.dist-info/RECORD
