Metadata-Version: 2.3
Name: sis-meta
Version: 1.0.0
Summary: Handle annotation files in SIS (Ikar Lab)
Project-URL: Documentation, https://github.com/unknown/sis-meta#readme
Project-URL: Issues, https://github.com/unknown/sis-meta/issues
Project-URL: Source, https://github.com/unknown/sis-meta
Author-email: rolandomunoz <rolando.muar@gmail.com>
License: GPL-3.0-or-later
Classifier: Development Status :: 4 - Beta
Classifier: Programming Language :: Python
Classifier: Programming Language :: Python :: 3.7
Classifier: Programming Language :: Python :: 3.8
Classifier: Programming Language :: Python :: 3.9
Classifier: Programming Language :: Python :: 3.10
Classifier: Programming Language :: Python :: 3.11
Classifier: Programming Language :: Python :: 3.12
Classifier: Programming Language :: Python :: 3.13
Classifier: Programming Language :: Python :: Implementation :: CPython
Classifier: Programming Language :: Python :: Implementation :: PyPy
Requires-Python: >=3.7
Requires-Dist: jinja2
Requires-Dist: markupsafe
